MANIFEST.in
README.md
setup.py
paybox/__init__.py
paybox/__version__.py
paybox/cli.py
paybox/exceptions.py
paybox/help.py
paybox/models.py
paybox/status_codes.py
paybox/utils.py
paybox.egg-info/PKG-INFO
paybox.egg-info/SOURCES.txt
paybox.egg-info/dependency_links.txt
paybox.egg-info/entry_points.txt
paybox.egg-info/not-zip-safe
paybox.egg-info/top_level.txt